pelican/plugins/show_source/__init__.py
pelican/plugins/show_source/show_source.py
pelican/plugins/test/data/content/articles/first.md
pelican/plugins/test/data/content/articles/second.md
pelican/plugins/test/data/content/articles/third.md
pelican/plugins/test/data/pelicanconf.py
pelican/plugins/test/data/templates/article.html
pelican/plugins/test/test_show_source.py
pelican_show_source-1.1.0.dist-info/WHEEL
pelican_show_source-1.1.0.dist-info/METADATA
pelican_show_source-1.1.0.dist-info/RECORD
